waretomo/__init__.py
waretomo/_aretomo.py
waretomo/_fix_mdoc.py
waretomo/_parse.py
waretomo/_stack.py
waretomo/_threaded.py
waretomo/_topaz.py
waretomo/main.py
waretomo/py.typed
waretomo-0.1.6.dist-info/METADATA
waretomo-0.1.6.dist-info/WHEEL
waretomo-0.1.6.dist-info/entry_points.txt
waretomo-0.1.6.dist-info/licenses/LICENSE
waretomo-0.1.6.dist-info/RECORD
