Metadata-Version: 2.3
Name: waretomo
Version: 0.1.6
Summary: Overengineered batch processing script for tomography data with Warp and aretomo.
Project-URL: homepage, https://github.com/brisvag/waretomo
Project-URL: repository, https://github.com/brisvag/waretomo
Author-email: Lorenzo Gaifas <brisvag@gmail.com>
License: GPLv3
License-File: LICENSE
Classifier: Development Status :: 3 - Alpha
Classifier: License :: OSI Approved :: GNU General Public License v3 (GPLv3)
Classifier: Natural Language :: English
Classifier: Programming Language :: Python :: 3
Classifier: Programming Language :: Python :: 3.9
Classifier: Programming Language :: Python :: 3.10
Classifier: Programming Language :: Python :: 3.11
Classifier: Typing :: Typed
Requires-Python: >=3.9
Requires-Dist: click
Requires-Dist: gputil
Requires-Dist: mdocfile==0.1.0
Requires-Dist: pandas
Requires-Dist: rich
Requires-Dist: sh
Requires-Dist: topaz-em==0.2.5
Provides-Extra: dev
Requires-Dist: black; extra == 'dev'
Requires-Dist: ipython; extra == 'dev'
Requires-Dist: pdbpp; extra == 'dev'
Requires-Dist: pre-commit; extra == 'dev'
Requires-Dist: pytest; extra == 'dev'
Requires-Dist: pytest-cov; extra == 'dev'
Requires-Dist: rich; extra == 'dev'
Requires-Dist: ruff; extra == 'dev'
Provides-Extra: test
Requires-Dist: pytest-cov; extra == 'test'
Requires-Dist: pytest>=6.0; extra == 'test'
